tests/__init__.py
tests/exemplars_test.py
tests/helpers.py
tests/regression.py
tests/seattle_benchmark.py
transit/__init__.py
transit/class_hash.py
transit/constants.py
transit/decoder.py
transit/helpers.py
transit/pyversion.py
transit/read_handlers.py
transit/reader.py
transit/rolling_cache.py
transit/sosjson.py
transit/transit_types.py
transit/write_handlers.py
transit/writer.py
transit_python-0.8.302.dist-info/DESCRIPTION.rst
transit_python-0.8.302.dist-info/METADATA
transit_python-0.8.302.dist-info/RECORD
transit_python-0.8.302.dist-info/WHEEL
transit_python-0.8.302.dist-info/metadata.json
transit_python-0.8.302.dist-info/top_level.txt
