Metadata-Version: 2.0
Name: transit-python
Version: 0.8.302
Summary: Transit marshalling for Python
Home-page: https://github.com/cognitect/transit-python
Author: Cognitect
Author-email: UNKNOWN
License: UNKNOWN
Platform: UNKNOWN
Requires-Dist: python-dateutil
Requires-Dist: msgpack-python
